{
  "Button": {
    "description": "Auto imported from components/Button.vue"
  },
  "LazyButton": {
    "description": "Auto imported from components/Button.vue"
  },
  "Card": {
    "description": "Auto imported from components/Card.vue"
  },
  "LazyCard": {
    "description": "Auto imported from components/Card.vue"
  },
  "LeaderBoard": {
    "description": "Auto imported from components/LeaderBoard.vue"
  },
  "LazyLeaderBoard": {
    "description": "Auto imported from components/LeaderBoard.vue"
  },
  "LobbyTable": {
    "description": "Auto imported from components/LobbyTable.vue"
  },
  "LazyLobbyTable": {
    "description": "Auto imported from components/LobbyTable.vue"
  },
  "Logo": {
    "description": "Auto imported from components/Logo.vue"
  },
  "LazyLogo": {
    "description": "Auto imported from components/Logo.vue"
  },
  "QuizzioLbl": {
    "description": "Auto imported from components/QuizzioLbl.vue"
  },
  "LazyQuizzioLbl": {
    "description": "Auto imported from components/QuizzioLbl.vue"
  }
}
